{"last_update": "2021/05/16, 05:00:00", "road_data": [{"parkway_mileposts": "234.1 - 242.3", "crossroads": "Mahogany Rock (NC) to Alligator Back Overlook", "status": "Open", "notes": "", "starting_milepost": "234.1", "ending_milepost": "242.3"}, {"parkway_mileposts": "237.1", "crossroads": "Air Bellows Gap Access Road", "status": "Open", "notes": "", "starting_milepost": "237.1", "ending_milepost": "237.1"}, {"parkway_mileposts": "242.3 - 285.5", "crossroads": "Alligator Back Overlook to Bamboo Gap", "status": "Ungated*", "notes": "", "starting_milepost": "242.3", "ending_milepost": "285.5"}, {"parkway_mileposts": "285.5 - 288.0", "crossroads": "Bamboo Gap to Aho Gap", "status": "Open", "notes": "", "starting_milepost": "285.5", "ending_milepost": "288.0"}, {"parkway_mileposts": "288.0 - 290.8", "crossroads": "Aho Gap to Green Hill Road", "status": "Ungated*", "notes": "", "starting_milepost": "288.0", "ending_milepost": "290.8"}, {"parkway_mileposts": "290.8 - 292.1", "crossroads": "Green Hill Road to US Highway 321/221 Blowing Rock", "status": "Open", "notes": "", "starting_milepost": "290.8", "ending_milepost": "292.1"}, {"parkway_mileposts": "292.1 - 294.5", "crossroads": "US Highway 321/221 Blowing Rock to Sandy Flat Gap, including Moses Cone Manor", "status": "Open", "notes": "", "starting_milepost": "292.1", "ending_milepost": "294.5"}, {"parkway_mileposts": "294.6 - 296.4", "crossroads": "Sandy Flat Gap to Price Park Picnic Area", "status": "Open", "notes": "PPCG A LOOP OPEN- First come, First served", "starting_milepost": "294.6", "ending_milepost": "296.4"}, {"parkway_mileposts": "296.4 - 298.5", "crossroads": "Price Park Picnic Area to Holloway Mountain Road", "status": "Ungated*", "notes": "", "starting_milepost": "296.4", "ending_milepost": "298.5"}, {"parkway_mileposts": "298.5 - 305.1", "crossroads": "Holloway Mountain Road to US Highway 221 (Beacon Heights)", "status": "Open", "notes": "", "starting_milepost": "298.5", "ending_milepost": "305.1"}, {"parkway_mileposts": "305.1 - 305.2", "crossroads": "US Highway 221 to Beacon Heights Overlook", "status": "Ungated*", "notes": "", "starting_milepost": "305.1", "ending_milepost": "305.2"}, {"parkway_mileposts": "305.2 - 307.9", "crossroads": "Beacon Heights Overlook to Roseboro Road", "status": "Open", "notes": "", "starting_milepost": "305.2", "ending_milepost": "307.9"}, {"parkway_mileposts": "307.9 - 314.6", "crossroads": "Roseboro Road to Shuffler Road/Parkway Road", "status": "Ungated*", "notes": "", "starting_milepost": "307.9", "ending_milepost": "314.6"}, {"parkway_mileposts": "314.6 - 317.5", "crossroads": "Shuffler Road/Parkway Road to US Highway 221 (Linville Falls)", "status": "Closed", "notes": "In addition to weather closures, Milepost 316.5-317.5 will be closed through summer 2021 for Linville Bridge repairs", "starting_milepost": "314.6", "ending_milepost": "317.5"}, {"parkway_mileposts": "316.5", "crossroads": "Linville Falls Spur Road", "status": "Open", "notes": "", "starting_milepost": "316.5", "ending_milepost": "316.5"}, {"parkway_mileposts": "317.5 - 324.7", "crossroads": "US Highway 221 to Jacksontown Access Road (Bear Den CG)", "status": "Open", "notes": "", "starting_milepost": "317.5", "ending_milepost": "324.7"}, {"parkway_mileposts": "324.7 - 330.9", "crossroads": "Jacksontown Access Road to NC Highway 226 (Gillespie Gap)", "status": "Ungated*", "notes": "", "starting_milepost": "324.7", "ending_milepost": "330.9"}, {"parkway_mileposts": "330.9 - 333.9", "crossroads": "NC Highway 226 (Gillespie Gap) to Little Switzerland", "status": "Open", "notes": "", "starting_milepost": "330.9", "ending_milepost": "333.9"}, {"parkway_mileposts": "333.9 - 342.1", "crossroads": "Little Switzerland to Victor Crossing", "status": "Open", "notes": "", "starting_milepost": "333.9", "ending_milepost": "342.1"}, {"parkway_mileposts": "342.1 - 344.2", "crossroads": "Victor Crossing to NC Highway 80", "status": "Ungated*", "notes": "", "starting_milepost": "342.1", "ending_milepost": "344.2"}, {"parkway_mileposts": "344.2 - 355.3", "crossroads": "NC Highway 80 to Mount Mitchell State Park", "status": "Open", "notes": "", "starting_milepost": "344.2", "ending_milepost": "355.3"}, {"parkway_mileposts": "355.3", "crossroads": "Mount Mitchell State Park", "status": "Open", "notes": "", "starting_milepost": "355.3", "ending_milepost": "355.3"}, {"parkway_mileposts": "355.3 - 364.5", "crossroads": "NC highway 128 to South of Craggy Gardens Tunnel, including Craggy Gardens Visitor Center", "status": "Open", "notes": "", "starting_milepost": "355.3", "ending_milepost": "364.5"}, {"parkway_mileposts": "364.5 - 367.6", "crossroads": "South of Craggy Gardens Tunnel to North of Craggy Gardens Picnic Area", "status": "Open", "notes": "", "starting_milepost": "364.5", "ending_milepost": "367.6"}, {"parkway_mileposts": "367.6 - 375.7", "crossroads": "North of Craggy Gardens Picnic Area to Bull Gap (Elk Mountain/Ox Creek Road)", "status": "Open", "notes": "", "starting_milepost": "367.6", "ending_milepost": "375.7"}, {"parkway_mileposts": "367.6", "crossroads": "USFS Road 63 (Stoney Fork Access Rd)", "status": "Open", "notes": "", "starting_milepost": "367.6", "ending_milepost": "367.6"}, {"parkway_mileposts": "375.7", "crossroads": "Ox Creek/Elk Mountain Access Road", "status": "Open", "notes": "", "starting_milepost": "375.7", "ending_milepost": "375.7"}, {"parkway_mileposts": "375.7 - 381.9", "crossroads": "Bull Gap (Elk Mountain/Ox Creek Road) to Folk Art Center", "status": "Open", "notes": "", "starting_milepost": "375.7", "ending_milepost": "381.9"}, {"parkway_mileposts": "377.4", "crossroads": "Craven Gap Access Road (Town Mountain Road)", "status": "Open", "notes": "", "starting_milepost": "377.4", "ending_milepost": "377.4"}, {"parkway_mileposts": "381.9 - 382.8", "crossroads": "Folk Art Center to Highway 70 (Tunnel Road)", "status": "Ungated*", "notes": "", "starting_milepost": "381.9", "ending_milepost": "382.8"}, {"parkway_mileposts": "382.8 - 384.1", "crossroads": "Highway 70 (Tunnel Road) to Park Headquarters and Visitor Center", "status": "Open", "notes": "", "starting_milepost": "382.8", "ending_milepost": "384.1"}, {"parkway_mileposts": "384.1 - 384.7", "crossroads": "Park Headquarters and Visitor Center to Highway 74 (I-40 Exit 53A)", "status": "Ungated*", "notes": "", "starting_milepost": "384.1", "ending_milepost": "384.7"}, {"parkway_mileposts": "384.7 - 388.8", "crossroads": "Highway 74 (I-40 Exit 53A) to Highway 25 (Hendersonville Road)", "status": "Open", "notes": "", "starting_milepost": "384.7", "ending_milepost": "388.8"}, {"parkway_mileposts": "388.8 - 393.6", "crossroads": "Highway 25 (Hendersonville Road) to NC Route 191 (Brevard Road)", "status": "Open", "notes": "", "starting_milepost": "388.8", "ending_milepost": "393.6"}, {"parkway_mileposts": "393.6 - 402.7", "crossroads": "NC Route 191 (Brevard Road) to Stoney Bald", "status": "Open", "notes": "", "starting_milepost": "393.6", "ending_milepost": "402.7"}, {"parkway_mileposts": "400.3", "crossroads": "USFS Road 5000 (Bent Creek Access Road)", "status": "Open", "notes": "", "starting_milepost": "400.3", "ending_milepost": "400.3"}, {"parkway_mileposts": "402.7 - 405.5", "crossroads": "Stoney Bald to NC Highway 151 Access Road", "status": "Open", "notes": "", "starting_milepost": "402.7", "ending_milepost": "405.5"}, {"parkway_mileposts": "405.5", "crossroads": "NC Highway 151 Access Road", "status": "Open", "notes": "", "starting_milepost": "405.5", "ending_milepost": "405.5"}, {"parkway_mileposts": "405.5 - 408.8", "crossroads": "Elk Pasture Gap to Pisgah Store", "status": "Open", "notes": "", "starting_milepost": "405.5", "ending_milepost": "408.8"}, {"parkway_mileposts": "408.8 - 411.9", "crossroads": "Pisgah Store (Pisgah Campground and Inn) to US Route 276", "status": "Open", "notes": "", "starting_milepost": "408.8", "ending_milepost": "411.9"}, {"parkway_mileposts": "411.9 - 418.7", "crossroads": "US Route 276 to North of Graveyard Fields Overlook", "status": "Open", "notes": "", "starting_milepost": "411.9", "ending_milepost": "418.7"}, {"parkway_mileposts": "418.7 - 420.2", "crossroads": "North of Graveyard Fields Overlook to USFS Road 816 (Black Balsam)", "status": "Open", "notes": "", "starting_milepost": "418.7", "ending_milepost": "420.2"}, {"parkway_mileposts": "420.2 - 423.2", "crossroads": "USFS Road 816 (Black Balsam) to Beech Gap (NC Route 215)", "status": "Open", "notes": "", "starting_milepost": "420.2", "ending_milepost": "423.2"}, {"parkway_mileposts": "423.2 - 443.0", "crossroads": "Beech Gap (NC Route 215) to Balsam Gap (US Route 23/74)", "status": "Open", "notes": "", "starting_milepost": "423.2", "ending_milepost": "443.0"}, {"parkway_mileposts": "443.0 - 455.7", "crossroads": "Balsam Gap (US Route 23/74) to Soco Gap (US Route 19)", "status": "Open", "notes": "", "starting_milepost": "443.0", "ending_milepost": "455.7"}, {"parkway_mileposts": "455.7 - 469.1", "crossroads": "Soco Gap (US Route 19) to US Route 441 thru Great Smoky Mtns. NP", "status": "Open", "notes": "", "starting_milepost": "455.7", "ending_milepost": "469.1"}, {"parkway_mileposts": "458.2", "crossroads": "Heintooga Spur Road", "status": "Open", "notes": "", "starting_milepost": "458.2", "ending_milepost": "458.2"}, {"parkway_mileposts": "469.1", "crossroads": "US Route 441 thru Great Smoky Mountains National Park", "status": "Visit Great Smoky Mtns NP website for updates", "starting_milepost": "469.1", "ending_milepost": "469.1"}]}